concord232-0.14.dist-info/metadata.json
concord232-0.14.dist-info/METADATA
concord232-0.14.dist-info/RECORD
concord232-0.14.dist-info/WHEEL
concord232-0.14.dist-info/DESCRIPTION.rst
concord232-0.14.dist-info/top_level.txt
concord232/concord_helpers.py
concord232/mail.py
concord232/api.py
concord232/concord_commands.py
concord232/concord_alarm_codes.py
concord232/main.py
concord232/concord_tokens.py
concord232/client.py
concord232/__init__.py
concord232/model.py
concord232/concord.py
concord232-0.14.data/scripts/concord232_server
concord232-0.14.data/scripts/concord232_client
