Metadata-Version: 2.0
Name: concord232
Version: 0.14
Summary: GE Concord 4 RS232 Serial Interface Library and Server
Home-page: http://github.com/JasonCarter80/concord232
Author: Jason Carter
Author-email: jason@jason-carter.net
License: UNKNOWN
Platform: UNKNOWN
Requires-Dist: requests
Requires-Dist: stevedore
Requires-Dist: prettytable
Requires-Dist: pyserial
Requires-Dist: flask
